mozcrash/__init__.py
mozcrash/mozcrash.py
mozcrash-2.2.0.dist-info/METADATA
mozcrash-2.2.0.dist-info/WHEEL
mozcrash-2.2.0.dist-info/top_level.txt
mozcrash-2.2.0.dist-info/RECORD
